TourchPIP/__init__.py
TourchPIP/backward/__init__.py
TourchPIP/backward/backprob.py
TourchPIP/dataset/CIFAR_10.py
TourchPIP/dataset/DataLoader.py
TourchPIP/dataset/FashionMNIST.py
TourchPIP/dataset/__init__.py
TourchPIP/forward/Activaions.py
TourchPIP/forward/Layers.py
TourchPIP/forward/Linear.py
TourchPIP/forward/NetWork.py
TourchPIP/forward/__init__.py
TourchPIP/losses/BiploarPerceptron.py
TourchPIP/losses/Biploar_SVM.py
TourchPIP/losses/MultiClassPerceptron.py
TourchPIP/losses/MultiClassSVM.py
TourchPIP/losses/MultiPerceptron.py
TourchPIP/losses/SD.py
TourchPIP/losses/SoftmaxCrossEntropy.py
TourchPIP/losses/__init__.py
TourchPIP/optimizations/__init__.py
TourchPIP/optimizations/adam.py
TourchPIP/optimizations/momentum.py
TourchPIP/optimizations/optimizer.py
TourchPIP-0.1.3.dist-info/LICENSE
TourchPIP-0.1.3.dist-info/METADATA
TourchPIP-0.1.3.dist-info/WHEEL
TourchPIP-0.1.3.dist-info/top_level.txt
TourchPIP-0.1.3.dist-info/RECORD
