Metadata-Version: 2.1
Name: TourchPIP
Version: 0.1.3
Summary: DL Framework help you to build simple neural network
Home-page: https://github.com/Mostafa-ashraf19/TourchPIP
Author: 
Author-email: 
License: MIT
Download-URL: https://github.com/Mostafa-ashraf19/TourchPIP/archive/v_01.3.tar.gz
Platform: UNKNOWN
Requires-Dist: numpy
Requires-Dist: pandas
Requires-Dist: matplotlib
Requires-Dist: requests
